{
    "display": {
        "title": {
            "text": "Wooden Tools",
            "color": "white"
        },
        "description": {
            "text": "The root of the upgrade tree. Has to be crafted.",
            "color": "aqua"
        },
        "icon": {
            "item": "minecraft:wooden_pickaxe"
        },
        "frame": "task",
        "show_toast": false,
        "announce_to_chat": false,
        "hidden": false
    },
    "criteria": {
        "tick": {
            "trigger": "minecraft:tick"
        }
    },
    "parent": "transmocraft:tcraft"
}
