{
  "parent": "minecraft:item/handheld",
  "overrides": [
    {
      "model": "transmocrafter:item/trim/sword/stone/quartz",
      "predicate": {
        "trim_type": 0.1
      }
    },
    {
      "model": "transmocrafter:item/trim/sword/stone/iron",
      "predicate": {
        "trim_type": 0.2
      }
    },
    {
      "model": "transmocrafter:item/trim/sword/stone/netherite",
      "predicate": {
        "trim_type": 0.3
      }
    },
    {
      "model": "transmocrafter:item/trim/sword/stone/redstone",
      "predicate": {
        "trim_type": 0.4
      }
    },
    {
      "model": "transmocrafter:item/trim/sword/stone/copper",
      "predicate": {
        "trim_type": 0.5
      }
    },
    {
      "model": "transmocrafter:item/trim/sword/stone/gold",
      "predicate": {
        "trim_type": 0.6
      }
    },
    {
      "model": "transmocrafter:item/trim/sword/stone/emerald",
      "predicate": {
        "trim_type": 0.7
      }
    },
    {
      "model": "transmocrafter:item/trim/sword/stone/diamond",
      "predicate": {
        "trim_type": 0.8
      }
    },
    {
      "model": "transmocrafter:item/trim/sword/stone/lapis",
      "predicate": {
        "trim_type": 0.9
      }
    },
    {
      "model": "transmocrafter:item/trim/sword/stone/amethyst",
      "predicate": {
        "trim_type": 1.0
      }
    }
  ],
  "textures": {
    "layer0": "minecraft:item/stone_sword"
  }
}
